[
  {
    "title": "diamond-partner",
    "logos": [
      {
        "name": "Arroyo Consulting",
        "url": "https://arroyoconsulting.net",
        "logoUrl": "../images/logos/ArroyoConsulting.png.webp",
        "height": 150,
        "width": 200
      }
    ]
  },
  {
    "title": "platinum-partner",
    "logos": [
      {
        "name": "Google",
        "url": "https://www.google.com.ua/intl/en/about",
        "logoUrl": "../images/logos/google.svg",
        "height": 100
      },
      {
        "name": "EvoPoint",
        "url": "https://www.evopoint.do/",
        "logoUrl": "../images/logos/evopoint.svg",
        "height": 75
      },
      {
        "name": "Oriontek",
        "url": "https://www.oriontek.do/",
        "logoUrl": "../images/logos/oriontek.jpg",
        "height": 100,
        "width": 200
      },
      {
        "name": "Solvex",
        "url": "https://solvex.com.do/",
        "logoUrl": "../images/logos/solvex.png",
        "height": 100,
        "width": 170
      },
      {
        "name": "UNPHU",
        "url": "https://unphu.edu.do",
        "logoUrl": "../images/logos/unphuLogo.png",
        "width": 200,
        "height": 85
      }
    
    ]
  },
  {
    "title": "gold-partner",
    "logos": [
      {
        "name": "Nearsure",
        "url": "https://nearsure.com",
        "logoUrl": "../images/logos/nearsure.png",
        "height": 75
      }
     
    ]
  },
  {
    "title": "silver-partner",
    "logos": [
      {
        "name": "Cecomsa",
        "url": "https://cecomsa.com",
        "logoUrl": "../images/logos/cecomsa.svg",
        "width": 200,
        "height": 85

      }
     
    ]
  },
  {
    "title": "other-partner",
    "logos": [
      {
        "name": "JetBrains",
        "url": "https://www.jetbrains.com/",
        "logoUrl": "../images/logos/jetbrains.svg",
        "width": 130,
        "height": 150
      },
      {
        "name": "Axure",
        "url": "https://www.axure.com/",
        "logoUrl": "../images/logos/axure.svg",
        "height": 85
      }
    ]
  }
]
